solvexia_sdk/__init__.py
solvexia_sdk/api.py
solvexia_sdk/datasteps/__init__.py
solvexia_sdk/datasteps/datasteps.py
solvexia_sdk/file/__init__.py
solvexia_sdk/file/file.py
solvexia_sdk/process/__init__.py
solvexia_sdk/process/process.py
solvexia_sdk/processrun/__init__.py
solvexia_sdk/processrun/processrun.py
solvexia_sdk/table/__init__.py
solvexia_sdk/table/table.py
solvexia_sdk/user/__init__.py
solvexia_sdk/user/user.py
solvexia_sdk/usergroup/__init__.py
solvexia_sdk/usergroup/usergroup.py
solvexia_sdk-1.3.2.dist-info/licenses/LICENCE
solvexia_sdk-1.3.2.dist-info/METADATA
solvexia_sdk-1.3.2.dist-info/WHEEL
solvexia_sdk-1.3.2.dist-info/top_level.txt
solvexia_sdk-1.3.2.dist-info/RECORD
