Metadata-Version: 2.4
Name: solvexia_sdk
Version: 1.3.2
Summary: A development kit written in Python to access and work with Solvexia resources
Home-page: https://github.com/solvexia/solvexia-python-sdk
Author: Solvexia Pty Ltd
Author-email: support@solvexia.com
License: GNU General Public License v3.0
Classifier: Programming Language :: Python :: 3
Classifier: License :: OSI Approved :: GNU General Public License v3 or later (GPLv3+)
Classifier: Operating System :: OS Independent
Requires-Python: >=3.6
License-File: LICENCE
Requires-Dist: filesplit>=4.1.0
Requires-Dist: readme-renderer>=29.0
Requires-Dist: requests>=2.25.1
Requires-Dist: requests-toolbelt>=0.9.1
Dynamic: author
Dynamic: author-email
Dynamic: classifier
Dynamic: description
Dynamic: description-content-type
Dynamic: home-page
Dynamic: license
Dynamic: license-file
Dynamic: requires-dist
Dynamic: requires-python
Dynamic: summary
